hipe4ml/__init__.py
hipe4ml/analysis_utils.py
hipe4ml/model_handler.py
hipe4ml/plot_utils.py
hipe4ml/tree_handler.py
hipe4ml-0.0.21.dist-info/LICENSE
hipe4ml-0.0.21.dist-info/METADATA
hipe4ml-0.0.21.dist-info/WHEEL
hipe4ml-0.0.21.dist-info/entry_points.txt
hipe4ml-0.0.21.dist-info/top_level.txt
hipe4ml-0.0.21.dist-info/RECORD
