Metadata-Version: 2.1
Name: hipe4ml
Version: 0.0.21
Summary: Minimal heavy ion physics environment for Machine Learning
Home-page: https://github.com/hipe4ml/hipe4ml
Author: hipe4ml-developers
Author-email: hipe4ml@googlegroups.com
License: GPL
Classifier: Development Status :: 3 - Alpha
Classifier: Intended Audience :: Education
Classifier: Intended Audience :: Developers
Classifier: Topic :: Scientific/Engineering :: Physics
Classifier: License :: OSI Approved :: GNU General Public License v3 (GPLv3)
Classifier: Programming Language :: Python :: 3.10
Classifier: Programming Language :: Python :: 3.11
Requires-Python: >=3.10
License-File: LICENSE
Requires-Dist: uproot>=4.2.2
Requires-Dist: matplotlib>=3.5.1
Requires-Dist: pandas>=1.3.5
Requires-Dist: scikit-learn<1.6,>=1.0.2
Requires-Dist: xgboost<2.0,>=1.5.2
Requires-Dist: lightgbm>=3.3.2
Requires-Dist: shap>=0.45
Requires-Dist: pyarrow>=7.0.0
Requires-Dist: ipython>=7.32.0
Requires-Dist: optuna>=2.10.0
Requires-Dist: numpy>=1.26
Provides-Extra: dev
Requires-Dist: pylint>=2.6.2; extra == "dev"
Requires-Dist: flake8>=3.8.4; extra == "dev"
Requires-Dist: pytest>=6.2.2; extra == "dev"
Requires-Dist: twine>=3.3.0; extra == "dev"
Requires-Dist: setuptools>=53.0.0; extra == "dev"
Requires-Dist: wheel>=0.36.2; extra == "dev"
